{
  "sources": [
    {
      "type": "nhk",
      "id": "nhk16",
      "path": "/data/nhk16_files",
      "display": "NHK16 %s"
    },
    {
      "type": "ajt_jp",
      "id": "shinmekai8",
      "path": "/data/shinmeikai8_files",
      "display": "SMK8 %s"
    },
    {
      "type": "forvo",
      "id": "forvo",
      "path": "/data/forvo_files",
      "display": "Forvo (%s)"
    },
    {
      "type": "jpod",
      "id": "jpod",
      "path": "/data/jpod_files",
      "display": "Jpod101"
    },
    {
      "type": "jpod",
      "id": "jpod_alternate",
      "path": "/data/jpod_alternate_files",
      "display": "JPod101 Alt"
    }
  ]
}
